sigma/backends/uberagent/__init__.py
sigma/backends/uberagent/exceptions.py
sigma/backends/uberagent/rule.py
sigma/backends/uberagent/uberagent.py
sigma/pipelines/uberagent/__init__.py
sigma/pipelines/uberagent/condition.py
sigma/pipelines/uberagent/field.py
sigma/pipelines/uberagent/logsource.py
sigma/pipelines/uberagent/transformation.py
sigma/pipelines/uberagent/uberagent.py
sigma/pipelines/uberagent/version.py
pysigma_backend_uberagent-0.3.69.dist-info/LICENSE
pysigma_backend_uberagent-0.3.69.dist-info/METADATA
pysigma_backend_uberagent-0.3.69.dist-info/WHEEL
pysigma_backend_uberagent-0.3.69.dist-info/RECORD
