Metadata-Version: 2.1
Name: pySigma-backend-uberAgent
Version: 0.3.69
Summary: pySigma uAQL backend
Home-page: https://github.com/vastlimits/pySigma-backend-uberAgent
License: MIT
Author: vast limits GmbH
Author-email: info@vastlimits.com
Requires-Python: >=3.8,<4.0
Classifier: License :: OSI Approved :: MIT License
Classifier: Programming Language :: Python :: 3
Classifier: Programming Language :: Python :: 3.8
Classifier: Programming Language :: Python :: 3.9
Classifier: Programming Language :: Python :: 3.10
Classifier: Programming Language :: Python :: 3.11
Classifier: Programming Language :: Python :: 3.12
Requires-Dist: pysigma (>=0.11.2,<0.12.0)
Project-URL: Repository, https://github.com/vastlimits/pySigma-backend-uberAgent
